SQLGetterSetter/__init__.py
sqlgettersetter-1.0.0.dist-info/METADATA
sqlgettersetter-1.0.0.dist-info/WHEEL
sqlgettersetter-1.0.0.dist-info/entry_points.txt
sqlgettersetter-1.0.0.dist-info/top_level.txt
sqlgettersetter-1.0.0.dist-info/RECORD
