Metadata-Version: 2.4
Name: SQLGetterSetter
Version: 1.0.0
Author: Kannan B
Requires-Dist: mysql-connector-python==9.1.0
Dynamic: author
Dynamic: description
Dynamic: description-content-type
Dynamic: requires-dist
